Twilly/__init__.py
Twilly/whatsappMessage.py
Twilly-0.0.3.dist-info/LICENSE
Twilly-0.0.3.dist-info/METADATA
Twilly-0.0.3.dist-info/WHEEL
Twilly-0.0.3.dist-info/top_level.txt
Twilly-0.0.3.dist-info/RECORD
