Metadata-Version: 2.1
Name: Twilly
Version: 0.0.3
Summary: A library to calculate real estate returns, taxes, stamp duty, and admin fees
Home-page: https://github.com/Ranji-Bhaskaran/Pypi_Library.git
Author: Ranjith Bhaskaran
Author-email: ranjithbhaskaran05@gmail.com
License: UNKNOWN
Platform: UNKNOWN
Classifier: Programming Language :: Python :: 3
Classifier: License :: OSI Approved :: MIT License
Classifier: Operating System :: OS Independent
Requires-Python: >=3.6
License-File: LICENSE
